pyyaml_rs/__init__.py
pyyaml_rs/pyyaml_rs.cpython-311-aarch64-linux-gnu.so
pyyaml_rs-0.1.0.dist-info/METADATA
pyyaml_rs-0.1.0.dist-info/WHEEL
pyyaml_rs-0.1.0.dist-info/RECORD
