Metadata-Version: 2.4
Name: pyyaml-rs
Version: 0.1.0
Classifier: Development Status :: 3 - Alpha
Classifier: Intended Audience :: Developers
Classifier: License :: OSI Approved :: MIT License
Classifier: Programming Language :: Python :: 3
Classifier: Programming Language :: Rust
Summary: High-performance Rust implementation of PyYAML
Keywords: yaml,rust,performance
License: MIT
Requires-Python: >=3.8
